pyfrac.py
pyfrac-0.0.1.dist-info/LICENSE.txt
pyfrac-0.0.1.dist-info/METADATA
pyfrac-0.0.1.dist-info/WHEEL
pyfrac-0.0.1.dist-info/top_level.txt
pyfrac-0.0.1.dist-info/RECORD
